mavetools/__init__.py
mavetools/client/__init__.py
mavetools/client/client.py
mavetools/client/util.py
mavetools/convert/__init__.py
mavetools/convert/enrich.py
mavetools/convert/enrich2/__init__.py
mavetools/convert/enrich2/base.py
mavetools/convert/enrich2/constants.py
mavetools/convert/enrich2/enrich2.py
mavetools/convert/enrich2/exceptions.py
mavetools/convert/enrich2/filters.py
mavetools/convert/enrich2/format.py
mavetools/convert/enrich2/utilities.py
mavetools/convert/enrich2/validators.py
mavetools/util/__init__.py
mavetools/util/codon.py
mavetools-0.3.0.dist-info/METADATA
mavetools-0.3.0.dist-info/WHEEL
mavetools-0.3.0.dist-info/licenses/LICENSE
mavetools-0.3.0.dist-info/RECORD
